RVBUST/__init__.py
RVBUST/Vis/PyVis.cpython-37m-x86_64-linux-gnu.so
RVBUST/Vis/__init__.py
rvbust_vis_test-1.0.0.dist-info/LICENSE
rvbust_vis_test-1.0.0.dist-info/METADATA
rvbust_vis_test-1.0.0.dist-info/WHEEL
rvbust_vis_test-1.0.0.dist-info/top_level.txt
rvbust_vis_test-1.0.0.dist-info/RECORD
