Metadata-Version: 2.1
Name: rvbust-vis-test
Version: 1.0.0
Summary: pip install Vis
Home-page: UNKNOWN
Author: rvbust
Author-email: hi@rvbust.com
License: MIT
Platform: UNKNOWN
Classifier: Programming Language :: Python :: 3
Classifier: License :: OSI Approved :: MIT License
Classifier: Operating System :: OS Independent
License-File: LICENSE
